tuna/__about__.py
tuna/__init__.py
tuna/__main__.py
tuna/_helpers.py
tuna/_import_profile.py
tuna/_runtime_profile.py
tuna/cli.py
tuna/magics.py
tuna/main.py
tuna/module_groups.py
tuna/web/index.html
tuna/web/static/bootstrap.min.css
tuna/web/static/d3.min.js
tuna/web/static/favicon256.png
tuna/web/static/icicle.js
tuna/web/static/tuna.css
tuna-0.5.11.dist-info/LICENSE.txt
tuna-0.5.11.dist-info/METADATA
tuna-0.5.11.dist-info/WHEEL
tuna-0.5.11.dist-info/entry_points.txt
tuna-0.5.11.dist-info/top_level.txt
tuna-0.5.11.dist-info/RECORD
